{
    "document_id": "doc_zs_zeeuwse_arbeidsmarkt_uitgave__1778587998",
    "source_clean_file": "Data\\silver\\doc_zs_zeeuwse_arbeidsmarkt_uitgave__1778587998_clean.txt",
    "language": "nl",
    "statistics": {
        "characters": 40837,
        "words": 5797,
        "sentences": 529,
        "entities_found_raw": 1025
    },
    "entities": {
        "persons": [],
        "organizations": [
            {
                "text": "UWV",
                "count": 24
            },
            {
                "text": "CBS",
                "count": 22
            },
            {
                "text": "LISA",
                "count": 6
            },
            {
                "text": "PAGINA",
                "count": 4
            },
            {
                "text": "MBO",
                "count": 4
            },
            {
                "text": "RIBIZ",
                "count": 3
            },
            {
                "text": "GWU",
                "count": 3
            },
            {
                "text": "Managers\nOpenbaar",
                "count": 3
            },
            {
                "text": "ICT",
                "count": 3
            },
            {
                "text": "Zeeuwse",
                "count": 2
            },
            {
                "text": "Gezondheids-en",
                "count": 2
            },
            {
                "text": "TOTAAL",
                "count": 2
            },
            {
                "text": "PROGNOSE",
                "count": 1
            },
            {
                "text": "VERWACHT",
                "count": 1
            },
            {
                "text": "TEKORT",
                "count": 1
            },
            {
                "text": "KNELPUNTEN",
                "count": 1
            },
            {
                "text": "TECHNISCHE",
                "count": 1
            },
            {
                "text": "Centraal Bureau voor de Statistiek",
                "count": 1
            },
            {
                "text": "Noord -Beveland",
                "count": 1
            },
            {
                "text": "Enquête Beroepsbevolking",
                "count": 1
            },
            {
                "text": "NVT",
                "count": 1
            },
            {
                "text": "UVW",
                "count": 1
            },
            {
                "text": "VMBO",
                "count": 1
            },
            {
                "text": "ZZP",
                "count": 1
            },
            {
                "text": "Managers\nIct beroepen",
                "count": 1
            }
        ],
        "locations": [
            {
                "text": "Zeeland",
                "count": 40
            },
            {
                "text": "Middelburg",
                "count": 6
            },
            {
                "text": "Kapelle",
                "count": 5
            },
            {
                "text": "gemeente Kapelle",
                "count": 5
            },
            {
                "text": "Creatieve",
                "count": 4
            },
            {
                "text": "Pedagogische",
                "count": 4
            },
            {
                "text": "Goes",
                "count": 4
            },
            {
                "text": "Planbureau",
                "count": 4
            },
            {
                "text": "Werkzame",
                "count": 3
            },
            {
                "text": "Bron",
                "count": 3
            },
            {
                "text": "Tholen",
                "count": 3
            },
            {
                "text": "Landelijk",
                "count": 2
            },
            {
                "text": "Zeeuws",
                "count": 2
            },
            {
                "text": "gemeente Vlissingen",
                "count": 2
            },
            {
                "text": "gemeente Hulst",
                "count": 2
            },
            {
                "text": "Hbo/bachelor",
                "count": 2
            },
            {
                "text": "KNELPUNTEN",
                "count": 1
            },
            {
                "text": "Provincie Zeeland",
                "count": 1
            },
            {
                "text": "Uitvoeringsinstituut",
                "count": 1
            },
            {
                "text": "provincie Zeeland",
                "count": 1
            },
            {
                "text": "Noot",
                "count": 1
            },
            {
                "text": "Vlaanderen",
                "count": 1
            },
            {
                "text": "Vlissingen",
                "count": 1
            },
            {
                "text": "Hulst",
                "count": 1
            },
            {
                "text": "Geregistreerde",
                "count": 1
            }
        ],
        "dates": [
            {
                "text": "augustus 2018",
                "count": 9
            },
            {
                "text": "75 jaar",
                "count": 7
            },
            {
                "text": "augustus",
                "count": 3
            },
            {
                "text": "november 2018",
                "count": 2
            },
            {
                "text": "vijf jaar",
                "count": 2
            },
            {
                "text": "januari 2017",
                "count": 2
            },
            {
                "text": "vier jaar",
                "count": 2
            },
            {
                "text": "November 2018",
                "count": 1
            },
            {
                "text": "2017)Bron",
                "count": 1
            },
            {
                "text": "15-74 jaar",
                "count": 1
            },
            {
                "text": "oktober 2017",
                "count": 1
            },
            {
                "text": "1 januari 2018",
                "count": 1
            },
            {
                "text": "januari 2016",
                "count": 1
            },
            {
                "text": "januari 2018",
                "count": 1
            },
            {
                "text": "t/m augustus 2018",
                "count": 1
            },
            {
                "text": "twee jaar eerder",
                "count": 1
            },
            {
                "text": "Juni 2016",
                "count": 1
            },
            {
                "text": "Juni 2017",
                "count": 1
            },
            {
                "text": "Juni 2018",
                "count": 1
            },
            {
                "text": "een half jaar",
                "count": 1
            },
            {
                "text": "15-67-jarigen",
                "count": 1
            },
            {
                "text": "60 tot 65 jaar",
                "count": 1
            },
            {
                "text": "900 zijn 55 tot 60 jaar",
                "count": 1
            },
            {
                "text": "65 tot 70 jaar",
                "count": 1
            },
            {
                "text": "41.900 Zeeuwse",
                "count": 1
            }
        ]
    },
    "keywords": [
        {
            "keyword": "beroepsbevolking",
            "count": 73
        },
        {
            "keyword": "aantal",
            "count": 64
        },
        {
            "keyword": "beroep",
            "count": 56
        },
        {
            "keyword": "persoon",
            "count": 46
        },
        {
            "keyword": "gemeente",
            "count": 45
        },
        {
            "keyword": "zeeland",
            "count": 42
        },
        {
            "keyword": "vacatures",
            "count": 38
        },
        {
            "keyword": "hoog",
            "count": 38
        },
        {
            "keyword": "bron",
            "count": 34
        },
        {
            "keyword": "figuur",
            "count": 30
        },
        {
            "keyword": "baan",
            "count": 29
        },
        {
            "keyword": "werkloos",
            "count": 27
        },
        {
            "keyword": "arbeidsaanbod",
            "count": 25
        },
        {
            "keyword": "sector",
            "count": 24
        },
        {
            "keyword": "laag",
            "count": 23
        },
        {
            "keyword": "technisch",
            "count": 22
        },
        {
            "keyword": "groot",
            "count": 22
        },
        {
            "keyword": "arbeidsvraag",
            "count": 22
        },
        {
            "keyword": "arbeidsparticipatie",
            "count": 22
        },
        {
            "keyword": "jaar",
            "count": 21
        },
        {
            "keyword": "tekort",
            "count": 18
        },
        {
            "keyword": "beroepsklasse",
            "count": 18
        },
        {
            "keyword": "percentage",
            "count": 17
        },
        {
            "keyword": "vacature",
            "count": 15
        },
        {
            "keyword": "nieuw",
            "count": 15
        },
        {
            "keyword": "krap",
            "count": 15
        },
        {
            "keyword": "arbeidmarkt",
            "count": 14
        },
        {
            "keyword": "verschillend",
            "count": 14
        },
        {
            "keyword": "verwachting",
            "count": 13
        },
        {
            "keyword": "augustus",
            "count": 13
        }
    ],
    "modeling_hints": {
        "main_topics": [
            "beroepsbevolking",
            "aantal",
            "beroep",
            "persoon",
            "gemeente",
            "zeeland",
            "vacatures",
            "hoog",
            "bron",
            "figuur"
        ],
        "important_entities": [
            "UWV",
            "CBS",
            "LISA",
            "PAGINA",
            "MBO",
            "RIBIZ",
            "GWU",
            "Managers\nOpenbaar",
            "ICT",
            "Zeeuwse",
            "Zeeland",
            "Middelburg",
            "Kapelle",
            "gemeente Kapelle",
            "Creatieve",
            "Pedagogische",
            "Goes",
            "Planbureau",
            "Werkzame",
            "Bron"
        ]
    },
    "processed_at": "2026-05-12T14:13:21.483698"
}